{"index":280,"number":680,"title":"Chapter 680. Ngươi nghĩ đây là đâu","source":"Hoa Sơn_/601-800/680.pdf","body":"Chapter 680. Ngươi nghĩ đây là đâu\nvậy hả? (5)\n\n\n\n“Hừmmm”\n\n\n\nTrường Nhất Tiếu mỉm cười nhìn bốn người đang tiến về phía\nmình.\n\n\n\nNơi này là Hoa Sơn.\n\n\n\nVà hắn đang đứng trước mặt Tứ Đại Môn Phái hàng đầu thiên hạ.\nThậm chí, các trưởng lão của Cửu Phái Nhất Bang và Ngũ Đại Thế\nGia trị vì thiên hạ cũng theo sau bọn họ.\n\n\n\nNếu hắn đã tự coi mình là người thuộc về Tà (邪) thì đây cũng là\ntình huống hắn không thể tránh khỏi.\n\n\n\nTuy nhiên, Trường Nhất Tiếu lại chẳng có chút thấp thỏm nào.\n\nBiểu cảm của hắn vô cùng thoải mái,\ngiống như nơi này cũng chỉ là mảnh sân trước ở Vạn Nhân Phòng.\n\n\n\nÁnh mắt Huyền Tông nhìn hắn có chút khác thường.\n\n\n\nÔng ta mím chặt môi. Thế nhưng, người khác không thể dễ dàng\nsuy đoán ông ta đang nghĩ gì. Huyền Tông chầm chậm cất lời.\n\n\n\n“Các hạ.”\n\n\n\n“.”\n\n\n\nMột âm thanh vô cùng điềm đạm, nhưng lại khiến Huyền Thương\nrùng mình.\n\n\n\n“Đang có rất nhiều tai mắt đấy, trưởng lão.”\n\n\n\n“.Vân Kiếm.”\n\nHuyền Thương khẽ liếc nhìn Vân Kiếm,\nrồi nhìn xuống phía tay áo rỗng của hắn.\n\n\n\nCũng chính vì lũ Vạn Nhân Phòng này mà Vân Kiếm đã đánh mất\ncánh tay của mình, đối mặt với ranh giới sinh tử. Và chỉ sơ sẩy một\nchút thôi, hắn sẽ không còn đứng ở đây lúc này rồi.\n\n\n\nẤy thế nhưng, Vân Kiếm lại ngăn cản Huyền Thương. Huyền\nThương tối sầm mặt, cắn chặt môi, nhìn chằm chằm vào Trường\nNhất Tiếu.\n\n\n\nVà đương nhiên, người có địch ý với Trường Nhất Tiếu không chỉ\ncó một mình Huyền Thương.\n\n\n\nCác đệ tử Hoa Sơn, ai nấy đều nắm chặt thanh kiếm bên hông,\nlặng lẽ nhìn hắn. Như thể chỉ cần có lệnh, là họ sẽ ngay lập tức\nxông đến chém đầu hắn.\n\n\n\nSát khí mà các đệ tử Hoa Sơn tỏa ra khiến các võ giả đang có mặt\nở đây cũng trở nên căng thẳng. Thế nhưng, Trường Nhất Tiếu lại\nvô cùng thản nhiên đón nhận số sát khí ấy.\n\n“Thật chẳng thể hiểu nổi.”\n\n\n\nHắn lắc đầu, tặc lưỡi như thể hắn không hiểu thật.\n\n\n\n“Vạn Nhân Phòng bọn ta cũng chịu thiệt hại lớn trong trận chiến\nvới Hoa Sơn. Do đó Vạn Nhân Phòng đã nhục nhã đến nỗi không\ndám ngẩng đầu khi ra giang hồ, còn Hoa Sơn lại thừa thắng xông\nlên nâng cao danh tiếng”\n\n\n\nHắn lắc lắc đầu.\n\n\n\n“Vì vậy ta thực sự không hiểu tại sao các vị lại nổi giận như thế\nnữa. Cứ phải bạc bẽo vô tình như vậy mới được gọi là đạo môn\nsao? Hừm.”\n\n\n\nHuyền Tông chậm rãi hít thở.\n\n\n\nTừng lời, từng lời của Trường Nhất Tiếu đều đập nát sự điềm tĩnh\nông ta đã tích lũy cả đời. Thế nhưng, ông ta đứng đây không phải\nvới tư cách là Chưởng môn nhân Hoa Sơn. Mà là Minh Chủ Thiên\nHữu Minh.\n\nVì vậy nên.\n\n\n\nHuyền Tông vòng hai tay đẩy ra phía trước.\n\n\n\n“Rất vui được gặp Bang Chủ Vạn Nhân Phòng.”\n\n\n\nThấy thế, Trường Nhất Tiếu cũng tạo thế bao quyền đáp lại.\n\n\n\n“Hân hạnh.”\n\n\n\nSau khi chào hỏi qua loa, Huyền Tông nở một nụ cười nhã nhặn\nhỏi Trường Nhất Tiếu.\n\n\n\n“Vạn Nhân Phòng vốn cách nơi này rất xa, tại sao ngươi phải cất\ncông tới tận Hoa Sơn vậy.”\n\n\n\nKhóe miệng Trường Nhất Tiếu ranh mãnh vén lên.\n\n“Chẳng lẽ lại còn lý do nào khác nữa sao.”\n\n\n\n“.”\n\n\n\n“Tất nhiên là bổn quân đến để chúc mừng lễ thành lập tân liên\nminh Thiên Hữu Minh rồi.”\n\n\n\n“..Chúc mừng?”\n\n\n\nTrường Nhất Tiếu gật đầu.\n\n\n\n“Bổn quân Trường Nhất Tiếu không dám nhận mình là đại nhân,\nnhưng cũng chẳng phải kẻ tiểu nhân đâu. Giang hồ có chuyện lớn\nthế này, sao bổn quân không tới chúc mừng cho được!”\n\n\n\n“.”\n\n\n\n“Mang lại đây!”\n\n“Vâng!”\n\n\n\nTrường Nhất Tiếu vừa dứt lời, các hộ vệ phía sau lưng hắn lập tức\nmang thứ gì đó tới.\n\n\n\n‘Rương ư?’\n\n\n\nBọn họ nâng trên vai ba cái rương, trông có vẻ khá to. Các võ giả\nkhông thể giấu nổi sự tò mò, khẽ nghểnh cổ tập trung quan sát.\n\n\n\nRầm! Rầm! Rầm!\n\n\n\nMỗi chiếc rương to đến mức tưởng chừng như có thể nhét cả một\nngười trong đó được hạ xuống.\n\n\n\n“Mở ra.”\n\n\n\n“Vâng!”\n\nLũ tay sai Vạn Nhân Phòng vội vàng mở nắp rương.\n\n\n\n“Ồ!”\n\n\n\n“Hừmmm!”\n\n\n\nCác võ giả cùng nhất loạt thốt ra những âm thanh kinh ngạc.\n\n\n\nTài bảo (財寶).\n\n\n\nThứ đầu tiên thu hút ánh nhìn của họ chính là những bảo hóa (寶\n貨) được chất đầy trong chiếc rương phía bên trái.\n\n\n\nHằng hà sa số kim tiền rực rỡ cùng bảo thạch lấp lánh được chất\nđầy trong chiếc rương lớn. Chúng nhiều đến mức ngay cả các\ntrưởng lão Võ Đang, những người đã được nhìn các bảo vật đến\nphát chán cũng không kìm nổi sự kinh ngạc.\n\n“Tiếp.”\n\n\n\n“Vâng!”\n\n\n\nChiếc rương thứ hai tiếp tục được mở ra. Những tiếng cảm thán\nđồng loạt vang lên như đã bị kìm nén rất lâu.\n\n\n\n“Hự!”\n\n\n\n“Đó, đó là.”\n\n\n\nBởi họ chỉ cần nhìn qua cũng biết, bên trong đó là những thanh\nbảo kiếm vô cùng sắc bén.\n\n\n\n‘Là thần binh!’\n\n\n\n‘Ôi trời ơi, đến mức đó luôn sao.’\n\n‘Quả nhiên tài sản của Vạn Nhân Phòng\nđủ để lấp kín thế gian này.’\n\n\n\nNếu chỉ xét theo vật giá, thì có lẽ, chiếc rương đầu tiên sẽ có giá\ntrị hơn. Tuy nhiên, đối với võ giả, bảo kiếm là thứ không thể dùng\ntiền để định giá được. Hơn nữa, chẳng phải bảo kiếm chính là thứ\ndù có ngàn vàng cũng chưa chắc có được sao.\n\n\n\nVậy mà Vạn Nhân Phòng lại đem tới cả một rương chất đầy bảo\nkiếm\n\n\n\nXoẹttttttt.\n\n\n\nMột tên thuộc hạ Vạn Nhân Phòng đứng trước rương, nhẹ nhàng\nrút ra thanh bảo kiếm trên cùng. Thanh kiếm vừa xuất hiện, tất cả\nđều thốt ra những âm thanh kinh ngạc.\n\n\n\nChỉ cần nhìn thôi cũng thấy, đây không phải bảo kiếm thông\nthường.\n\nCác võ giả nuốt khan nhìn về phía chiếc\nrương thứ ba. Hai cái rương đầu tiên đã chứa rất nhiều thứ có giá\ntrị rồi, không biết, chiếc rương cuối cùng này sẽ chứa thì gì đây.\n\n\n\nTrường Nhất Tiếu cao cao tự đại nói như thể hắn sẽ không phụ\nlòng kỳ vọng ấy.\n\n\n\n“Mở ra đi.”\n\n\n\n“Rõ!”\n\nNắp rương cuối cùng được mở ra. Một mùi hương vô cùng tươi\nmát phả vào mũi các võ giả. Chỉ nhiêu đó cũng đủ để họ biết bên\ntrong chiếc rương ấy đựng thứ gì.\n\n\n\n‘Là linh dược!’\n\n\n\n‘Tất cả chỗ đó’\n\n\n\nMột sự im lặng bao trùm.\n\nGiá trị của những thứ đó đều vượt qua\nsức tưởng tượng của bọn họ. Nếu không có thuộc hạ của Vạn\nNhân Phòng đang bao quanh chiếc rương đó thì có lẽ một vài\nngười đã sớm chạy ra đó rồi. Lòng tham tràn ngập trong ánh mắt\ncủa các võ giả. Tim họ bắt đầu đập thình thịch.\n\n\n\n“Đây là quà chúc mừng lễ thành lập tân liên minh Thiên Hữu\nMinh.”\n\n\n\nTrường Nhất Tiếu thong thả cười nhìn Huyền Tông.\n\n\n\nThế nhưng, Huyền Tông lại chỉ nhìn số bảo vật Trường Nhất Tiếu\nmang tới rồi thở dài như thể ông ta đang vô cùng sầu não.\n\n\n\n“Bổn Minh Chủ rất cảm kích tấm lòng của Bang Chủ, chỉ có điều,\ngọi chúng là quà mừng lễ thành lập thì có chút hơi quá rồi.”\n\n\n\n“Hơi quá ư?”\n\n\n\nTrường Nhất Tiếu vén môi như thể điều ấy thật nực cười.\n\n“Minh Chủ. Bổn quân là Trường Nhất Tiếu.”\n\n\n\n“.”\n\n\n\n“Đối với bổn quân thì nhiêu đây không thể gọi là quá được. Bổn\nquân còn nghĩ, chúng vẫn chưa đủ để thể hiện tấm lòng của bổn\nquân đối với Thiên Hữu Minh.”\n\n\n\nHuyền Tông bỏ qua lời nói ấy như thể nó chẳng quan trọng mấy.\nBởi vì điều quan trọng nhất bây giờ chính là cảnh tượng khi nãy\nđã khiến các quan khách vô cùng bất ngờ.\n\n\n\n“Hơn nữa.”\n\n\n\nTrường Nhất Tiếu mỉm cười nhìn các trưởng lão Cửu Phái Nhất\nBang và Ngũ Đại Thế Gia đang đứng phía sau Huyền Tông.\n\n\n\n“Chỉ chúc bằng miệng thì đâu phải lời chúc thật lòng. Nếu các\nngài thật lòng muốn chúc mừng thì các ngài cũng phải mang đến\n\nthứ gì đó đáng giá một chút chứ. Đó\nkhông phải là chuyện đương nhiên sao?”\n\n\n\nRầm! Rầm! Rầm!\n\n\n\nTrường Nhất Tiếu vừa ngắt lời, các nắp rương đã lần lượt được\nđóng lại. Thuộc hạ của hắn đẩy những chiếc rương về phía trước\nmặt Huyền Tông.\n\n\n\n“Ngài thấy sao? Nhiêu đây đã đủ để chứng minh sự chân thành\ncủa bổn quân rồi chứ?”\n\n\n\nHuyền Tông yên lặng nhìn Trường Nhất Tiếu.\n\n\n\nTrường Nhất Tiếu mỉm cười trước ánh mắt không có chút dao\nđộng nào của Huyền Tông. Rồi hắn nhẹ nhàng nói.\n\n\n\n“Ơ kìa Minh Chủ. Đúng là nực cười thật nhỉ?”\n\n\n\n“.”\n\n“Vì Hoa Sơn mà Vạn Nhân Phòng đã phải chịu tổn thất rất lớn, ấy\nvậy mà bọn ta vẫn cất công mang quà tới tận nơi này. Trong khi\nđó Hoa Sơn đã nhận được rất nhiều lợi ích từ Vạn Nhân Phòng,\nvậy mà Minh Chủ ngài vẫn không thể quên được mối tư thù nhỏ\nnhặt đó mà bạc đãi khách như vậy sao.”\n\n\n\nHắn vừa dứt câu, gương mặt các đệ tử Hoa Sơn đã tối sầm lại.\n\n\n\n“Nếu cứ thế này thì làm sao Minh Chủ Thiên Hữu Minh có thể\nthâu tóm các môn phái nhỏ hơn được.”\n\n\n\n“Tên khốn khiếp này!”\n\n\n\nThanh Minh không thể nhịn được nữa, hét lớn. Đến cả Bạch Thiên\nthường ngày đứng ra ngăn cản hắn cũng yên lặng. Bởi vì chính\nBạch Thiên cũng đang nắm chặt lấy kiếm, tỏa ra một luồng sát\nkhí lạnh lùng.\n\n\n\nKhóe môi Trường Nhất Tiếu càng cong lên.\n\nMột sự chế giễu quá rõ ràng.\n\n\n\nMục Hạ Vô Nhân quả thật rất hợp với hắn trong hoàn cảnh này.\nTuy hắn nói tới đây để chúc mừng, nhưng từng lời nói, từng hành\nđộng của hắn lại chỉ toàn mỉa mai, chế giễu.\n\n\n\nVà lý do hắn dám hống hách, kiêu ngạo như vậy cũng chính bởi vì\nhắn là Bá Quân Trường Nhất Tiếu.\n\n\n\n‘..Nặng quá.’\n\n\n\nBạch Thiên cắn chặt môi. Dường như toàn thân hắn đang bị đè\nnặng từ nãy tới giờ.\n\n\n\nBạch Thiên không thể biết được hắn là kẻ tàn nhẫn và mạnh đến\nmức nào.\n\n\n\nMới đối diện với hắn một lần thôi mà Bạch Thiên đã cảm nhận\nđược một áp lực chưa từng có. Trường Nhất Tiếu chỉ đứng đó thôi\ncũng đã đè bẹp biết bao võ giả ở đây chỉ bằng khí thế của hắn.\n\nĐó mới chính là cảm giác áp đảo thực sự.\n\n\n\n‘..Hắn là Bá Quân.’\n\n\n\nTên tuổi và danh tiếng của hắn đã khiến cho rất nhiều đệ tử Hoa\nSơn mất hết khí thế. Nhưng đây chính là lần đầu tiên sự tồn tại\ncủa Trường Nhất Tiếu khiến họ phải nghẹt thở.\n\n\n\n‘Cảm giác này, ngay cả Ngụy Giáo Chủ Ma Giáo cũng chẳng có\nđược.’\n\n\n\nTay hắn run rẩy. Bạch Thiên liếc mắt nhìn Thanh Minh đang đứng\ntrên hắn một bước chân.\n\n\n\nLưng của hắn không nhúc nhích chút nào.\n\n\n\nThanh Minh đang nghĩ gì?\n\nĐúng lúc ấy, Trường Nhất Tiếu lại nói\ntiếp.\n\n\n\n“Vốn dĩ bổn quân chỉ tới để xem Hoa Sơn, và Thiên Hữu Minh vĩ\nđại đến mức nào, nhưng sự thật lại khiến bổn quân quá thất vọng.\nHa, đúng là mất hứng.”\n\n\n\nHắn cảnh giác, chầm chậm liếc nhìn tất cả các võ giả đang cố nín\nthở kia. Chỉ những kẻ không có khí phách mới không dám đối mặt\nvới hắn.\n\n\n\n“Về thôi.”\n\n\n\nĐúng lúc Trường Nhất Tiếu cười khẩy định quay người bước đi.\n\n\n\n“Chúc mừng ư”\n\n\n\n“.”\n\nTrường Nhất Tiếu quay đầu nhìn Huyền\nTông, người vừa phát ra âm thanh trầm tĩnh ấy.\n\n\n\n“Đúng như Bang Chủ nói, đó không phải là chuyện chỉ nói bằng\nmiệng.”\n\n\n\n“Ồ hô?”\n\n\n\nMột giọng nói điềm tĩnh tới mức không có chút dao động nào.\n\nTuy là Chưởng môn nhân của Hoa Sơn, nhưng mãi đến gần đây,\nHuyền Tông vẫn chỉ là Chưởng môn nhân của một môn phái hạng\nba. Một người như vậy lại dám nhìn thẳng vào Trường Nhất Tiếu\nđã khiến hắn cảm thấy vô cùng hứng thú.\n\n\n\n“Vậy nên bổn Minh Chủ muốn hỏi.”\n\n\n\n“.”\n\n\n\n“Bá Quân muốn nhìn thấy điều gì?”\n\nÁnh mắt trầm mặc như hồ nước sâu của\nHuyền Tông giao với ánh mắt rừng rực như ngọn lửa của Trường\nNhất Tiếu.\n\n\n\n“.Không tệ.”\n\n\n\nTrường Nhất Tiếu gật đầu.\n\n\n\nRồi hắn quay người về phía Huyền Tông, dang tay như thể đang\nrất vui vẻ. Tiếng va chạm giữa những món trang sức đang được\nđeo lủng lẳng vang lên.\n\n\n\n“Ngài hỏi bổn quân muốn gì ư?”\n\n\n\n“Phải.”\n\n\n\n“Ừm. Điều bổn quân muốn.”\n\n\n\nTrường Nhất Tiếu nở một nụ cười đầy ẩn ý.\n\n“Ngài thấy chuyện này thế nào?”\n\n\n\n“?”\n\n\n\n“Minh Chủ thấy sao”\n\n\n\nĐôi môi đỏ mọng của hắn nở một nụ cười mê đắm.\n\n\n\n“Nếu Vạn Nhân Phòng muốn trở thành huynh đệ với Thiên Hữu\nMinh?”\n\n\n\nMột luồng khí rùng rợn và lạnh lẽo như thể có một thanh kiếm\nsắc bén đang kề ngay cổ bùng lên, lan tỏa khắp Hoa Sơn."}