{
  "index": 376,
  "number": 846,
  "rangeEnd": null,
  "title": "Chapter 846. Hoa Sơn mà không có",
  "source": "Hoa Sơn_/800-1000/846.pdf",
  "body": "Truyện được mua và tổng hợp bởi page Hoa Sơn Tái Khởi ,\nlink https://www.facebook.com/hoasontaikhoifull\nTruyện được mua và tổng hợp bởi page Hoa Sơn Tái Khởi , link\nhttps://www.facebook.com/hoasontaikhoifull\nChapter 846. Hoa Sơn mà không có\ncác con thì chẳng còn là Hoa Sơn nữa. (1)\n“Hể?”\n“Hả?”\n“Ể ể ể?”\n“Hơ?”\n“Người vừa nói gì cơ?”\nTuy rằng mỗi người một phản ứng khác nhau, thế nhưng, trong\nmắt ai nấy đều tràn ngập lo lắng.\nCác đệ tử Hoa Sơn đứng bao quanh Huyền Tông liên tục chớp\nmắt.\nCác đệ tử ngơ ngác hết nhìn Huyền Tông lại quay sang nhìn\nnhau. Như thể muốn nói không chỉ một mình ta nghe nhầm.\n“Ch…… Chưởng Môn Nhân?”\nBạch Thương thận trọng nghiêng đầu nói.\n\nTruyện được mua và tổng hợp bởi page Hoa Sơn Tái Khởi ,\nlink https://www.facebook.com/hoasontaikhoifull\nTruyện được mua và tổng hợp bởi page Hoa Sơn Tái Khởi , link\nhttps://www.facebook.com/hoasontaikhoifull\n“Nếu…… nếu con nghe không nhầm\nthì…… thì……”\nHắn không ngừng liếc nhìn xung quanh. Để xác nhận không chỉ\nmình hắn chưa hiểu tình hình lúc này.\nTuy rằng hắn mong mình đã nghe nhầm, nhưng khi vừa đối mắt\nvới hắn, các huynh đệ của hắn ngay lập tức gập đầu. Điều đó có\nnghĩa là những gì hắn vừa nghe không hề sai.\n“Người…… người vừa nói….. phong….. bế sơn môn ư……?”\nBạch Thương vừa nói vừa cười bất lực.\nPhong bế sơn môn.\nAi mà tin được chuyện này chứ……\n“.......Đúng vậy.”\n“Hể ể ể?”\n“Dạ?”\n“Người vừa nói gì cơ?”\n\nTruyện được mua và tổng hợp bởi page Hoa Sơn Tái Khởi ,\nlink https://www.facebook.com/hoasontaikhoifull\nTruyện được mua và tổng hợp bởi page Hoa Sơn Tái Khởi , link\nhttps://www.facebook.com/hoasontaikhoifull\n“Chúng ta á?”\nCác đệ tử Hoa Sơn đồng loạt lên cơn co giật sau khi sự thật đã\nđược xác nhận. Và tất nhiên, người phản ứng kịch liệt nhất chính\nlà Chiêu Kiệt.\n“Ơ không, Chưởng Môn Nhân! Chúng con có gây ra tội gì đâu,\nsao người lại phong bế sơn môn! Nếu như có tên nào trong số\ncác đệ tử lừa đảo…… Áaaaaaa!”\n“Câm miệng lại ngay, cái tên chết tiệt này! Câm miệng lại ngay!”\nNhuận Tông nhanh như chớp túm cổ áo Chiêu Kiệt, liên tục giáng\nnhững cú đấm vào cằm khiến hắn ngất xỉu.\n“Hừ.”\nNhuận Tông một tay hắn túm lấy Chiêu Kiệt, một tay đưa lên\nmiệng khe ho một tiếng. Tuy rằng cảnh tượng ấy chẳng hài hòa\nchút nào, thế nhưng lúc này, chẳng có ai còn tâm trạng quan tâm\ntới chuyện đó.\n\nTruyện được mua và tổng hợp bởi page Hoa Sơn Tái Khởi ,\nlink https://www.facebook.com/hoasontaikhoifull\nTruyện được mua và tổng hợp bởi page Hoa Sơn Tái Khởi , link\nhttps://www.facebook.com/hoasontaikhoifull\n“.......Chưởng Môn Nhân, người làm\nchúng con bối rối quá. Con biết phải có chuyện gì đó thì người\nmới nói thế, nhưng đột nhiên người lại phong bế sơn môn như\nvậy.”\nTất cả cùng kịch liệt gật đầu.\nThấy những ánh mắt yêu cầu đưa ra lời giải thích dồn hết về phía\nmình, Huyền Tông khẽ chậm rãi quay đầu. Cuối cùng, ánh mắt\ncủa ông ta hướng về phía Thanh Minh.\nThanh Minh nở nụ cười tươi rói.\nChiêu Kiệt đang mơ hồ hét lên một tiếng dữ dội, vùng khỏi tay\nNhuận Tông chạy tới túm lấy cổ áo Bạch Thiên.\n“Rốt cuộc là người đã làm gì vậy?! Hả, cái con người này! Con\nhỏi là rốt cuộc người đã làm gì!”\nMặc dù việc sư điệt nắm lấy cổ áo sư thúc là chuyện khiến thiên\nnhân phẫn nộ, thế nhưng, Bạch Thiên lại chẳng hề nổi giận. Mà\nkhông, phải là hắn không thể bộc lộ sự tức giận. Hắn chỉ đang\n\nTruyện được mua và tổng hợp bởi page Hoa Sơn Tái Khởi ,\nlink https://www.facebook.com/hoasontaikhoifull\nTruyện được mua và tổng hợp bởi page Hoa Sơn Tái Khởi , link\nhttps://www.facebook.com/hoasontaikhoifull\nngượng ngùng cố gắng né tránh ánh\nmắt hừng hực của Chiêu Kiệt.\n“Hơ……. tiểu tử đó mới là người gây chuyện mà, sao con lại làm\nvậy với ta?”\n“Không có lửa làm sao có khói? Sư thúc nói cái tên châm lửa đó\nlà kẻ sai đúng không? Nhưng nó thì sai gì chứ? Chẳng phải lỗi là\nở sư thúc đã khiến cho tên điên đó phấn khích sao!”\nMặc dù Chiêu Kiệt đang thốt ra những lời vô lễ, nhưng các đệ tử\nHoa Sơn đang có mặt ở nơi này đều nhiệt liệt đồng ý với hắn.\nThậm chí, sâu thẳm trong lòng, Bạch Thiên cũng đang cảm thấy\ncó lỗi.\n“Sao ta biết được mọi chuyện sẽ tới nước này chứ…….”\nNgười bình thường làm sao có thể biết được một kẻ điên đang\nnghĩ gì.\n\nTruyện được mua và tổng hợp bởi page Hoa Sơn Tái Khởi ,\nlink https://www.facebook.com/hoasontaikhoifull\nTruyện được mua và tổng hợp bởi page Hoa Sơn Tái Khởi , link\nhttps://www.facebook.com/hoasontaikhoifull\nPhong bế sơn môn. Tin này chẳng khác\nnào sét đánh giữa trời quang.\n“.......Chưởng Môn Nhân. Rốt cuộc, người đã nghe được chuyện\ngì mà tự nhiên lại……”\nNhuận Tông ngơ ngác hết nhìn Thanh Minh lại nhìn Huyền Tông,\nrun rẩy nói.\n“Tất nhiên là……. cho dù là lý do gì đi chăng nữa, thì phận hậu\nbối như chúng con sẽ luôn phải tuân theo lệnh của Chưởng Môn\nNhân, nhưng ít ra, thì con cũng muốn biết lý do.”\n“Chuyện đó……..”\n“Vâng, Chưởng Môn Nhân.”\n“Chuyện đó……..”\nKhóe mắt Huyền Tông dần trở nên ươn ướt.\nNhuận Tông chẳng dám hỏi thêm khi chứng kiến cảnh tượng ấy.\nNhuận Tông hung dữ quay đầu.\n\nTruyện được mua và tổng hợp bởi page Hoa Sơn Tái Khởi ,\nlink https://www.facebook.com/hoasontaikhoifull\nTruyện được mua và tổng hợp bởi page Hoa Sơn Tái Khởi , link\nhttps://www.facebook.com/hoasontaikhoifull\n“Đệ hãy giải thích đi, cái tên chết bầm\nnày! Sao tự dưng lại phong bế sơn môn hả?! Bọn ta có gây nên\ntội gì đâu!”\n“Sư huynh nói gì nghe lạ quá.”\nThanh Minh ngoáy ngoáy tai rồi đưa lên miệng thổi phù.\n“Ta cũng có phải là người đưa ra quyết định phong bế sơn môn\nđâu, ta chỉ là một đệ tử đời thứ ba không có chút uy quyền gì thôi\nmà?”\n“Một đệ tử đời thứ ba không có chút uy quyền gì? Không có chút\nuy quyền gì ư?”\nTiểu tử đáng ghét.\n“Hơn nữa, tại sao cứ phải gây ra tội mới được phong bế sơn\nmôn? Sư huynh nghĩ vậy là do lúc nào sư huynh cũng thấy lũ\nCửu Phái Nhất Bang phong bế, trốn chui trốn nhủi trong sơn môn\nsau khi gây tội vì không muốn nghe người đời chửi mắng mình\n\nTruyện được mua và tổng hợp bởi page Hoa Sơn Tái Khởi ,\nlink https://www.facebook.com/hoasontaikhoifull\nTruyện được mua và tổng hợp bởi page Hoa Sơn Tái Khởi , link\nhttps://www.facebook.com/hoasontaikhoifull\nthôi. Chứ ngay từ đầu, phong bế sơn\nmôn đã là chuyện thích là làm rồi.”\n“Vậy nên ta mới hỏi sao lại là ngay lúc này đấy!”\nBạch Thương vội vàng đứng ra nói đỡ cho Nhuận Tông.\n“Phải đấy, tiểu tử chết tiệt! Bây giờ đang là lúc nào kia chứ! Cả\nthế gian đang tán dương Hoa Sơn! Công việc kinh doanh thì làm\năn phát đạt càng như hổ mọc thêm cánh! Đây chính là thời điểm\nngười đời nhắc tới Hoa Sơn còn nhiều hơn cả Cửu Phái Nhất\nBang! Nước xuôi dòng thì càng phải chèo chứ! Con muốn đi\nngược dòng để rồi bị đánh cho lật thuyền à? Hả? Cái….. cái tên\nđiên này!”\nBạch Thương vỗ bôm bốp vào ngực như thể hắn đang vô cùng\nbức bối.\n“Người đừng đứng yên như vậy nữa, người hãy nói gì đi chứ,\nCác Chủ!”\n\nTruyện được mua và tổng hợp bởi page Hoa Sơn Tái Khởi ,\nlink https://www.facebook.com/hoasontaikhoifull\nTruyện được mua và tổng hợp bởi page Hoa Sơn Tái Khởi , link\nhttps://www.facebook.com/hoasontaikhoifull\nRồi hắn quay sang Huyền Linh tìm chi\nviện. Thế nhưng, Huyền Linh lại chỉ nói với một vẻ mặt kiên\nquyết.\n“Chắc hẳn Thanh Minh đã có suy tính riêng.”\n“Trời ơi!”\nĐúng là cùng một giuộc mà!\nĐúng lúc, Chiêu Kiệt đang túm lấy cổ áo Bạch Thiên vội vàng đảo\nmắt rồi chạy về phía Thanh Minh.\n“Này, tên điên kia……! Áaaa!”\nChiêu Kiệt lao tới bị đá cho một cái ngã lăn vài vòng trên mặt đất.\nMột điều đáng buồn là chẳng ai thèm tới đỡ hắn lại.\n“Chậc.”\nThanh Minh co chân lại, tặc lưỡi nhìn xung quanh.\n“Hình như mọi người đang hiểu lầm rồi.”\n“Hả?”\n\nTruyện được mua và tổng hợp bởi page Hoa Sơn Tái Khởi ,\nlink https://www.facebook.com/hoasontaikhoifull\nTruyện được mua và tổng hợp bởi page Hoa Sơn Tái Khởi , link\nhttps://www.facebook.com/hoasontaikhoifull\n“Đây không phải là ý kiến của ta.”\n“Hả? Vậy thì là ai?”\nThanh Minh nghiêm túc nhắm mắt, gật đầu.\n“Ta chỉ đang làm theo những gì Bạch Thiên sư thúc sai bảo thôi.\nChẳng phải bổn phận của sư điệt là phải làm theo lời sư thúc\nsao?”\nMọi ánh mắt đổ dồn về phía Bạch Thiên.\nBạch Thiên nở một nụ cười ôn hòa.\n“.........Tại nó nói sẽ đánh chết ta. Nó nói sẽ ban cho ta một cái\nchết đẹp đẽ, không đau khổ.”\n“Ta bắt nạt sư thúc bao giờ? Sư thúc quá lời rồi đấy.”\nBạch Thiên ôm mặt cúi gục đầu, hai vai run rẩy.\n“Chưởng Môn Nhân! Người thực sự sẽ nghe theo những lời vô lý\nấy sao?”\n\nTruyện được mua và tổng hợp bởi page Hoa Sơn Tái Khởi ,\nlink https://www.facebook.com/hoasontaikhoifull\nTruyện được mua và tổng hợp bởi page Hoa Sơn Tái Khởi , link\nhttps://www.facebook.com/hoasontaikhoifull\n“Cho dù nó là Thanh Minh đi chăng nữa,\nnhưng chẳng phải chuyện lần này có hơi quá rồi sao?”\n“Con không thể chấp nhận được! Phong bế sơn môn gì chứ. Tại\nsao chúng ta lại phải phong bế sơn môn? Kẻ gây tội là Thiếu Lâm\nvà Võ Đang, nếu chúng ta phong bế sơn môn thì thiên hạ sẽ nghĩ\ngì về chúng ta đây?”\nThấy các đệ tử hừng hực khí thế đứng bật dậy, Huyền Tông trầm\ntĩnh lướt nhìn tất cả bọn họ một lượt.\nĐúng lúc ấy, một giọng nói nhẹ nhàng phát ra khiến tất cả trở nên\nyên lặng.\n“Phong bế sơn môn.”\nÁnh mắt của các đệ tử đổ dồn về một nơi. Lưu Lê Tuyết thản\nnhiên gật đầu.\n“Quay trở về Hoa Sơn rồi phong bế sơn môn.”\n“…….”\n\nTruyện được mua và tổng hợp bởi page Hoa Sơn Tái Khởi ,\nlink https://www.facebook.com/hoasontaikhoifull\nTruyện được mua và tổng hợp bởi page Hoa Sơn Tái Khởi , link\nhttps://www.facebook.com/hoasontaikhoifull\n“Cũng tốt.”\nCác đệ tử khẽ liếc nhìn nhau.\n‘Ơ, sao sư muội lại như vậy.’\n‘Ai mà biết được muội ấy đang suy nghĩ gì!’\n‘Đúng là càng lúc càng điên.’\nNếu Thanh Minh là một cơn bão mà ai cũng có thể nhìn thấy nó\nđang từ xa tiến lại, thì Lưu Lê Tuyết lại là một cơn địa chấn bất\nngờ ập tới. Con người có thể phòng chống bão, nhưng chẳng thể\ntránh khỏi địa chấn.\n“Dù sao thì mọi chuyện cũng đã như vậy rồi, mọi người hãy\nchuẩn bị quay về Hoa Sơn đi.”\n“Ơ không, tên chết tiệt này!”\n“Rốt cuộc chuyện gì đang xảy ra thế này!”\nBạch Thiên vốn luôn yên lặng bỗng lên tiếng.\n“Thanh Minh.”\n\nTruyện được mua và tổng hợp bởi page Hoa Sơn Tái Khởi ,\nlink https://www.facebook.com/hoasontaikhoifull\nTruyện được mua và tổng hợp bởi page Hoa Sơn Tái Khởi , link\nhttps://www.facebook.com/hoasontaikhoifull\n“Hửm?”\nGương mặt của hắn trở nên nghiêm túc.\n“Con hãy giải thích cho mọi người hiểu trước đi. Đây đâu phải là\nviệc có thể qua loa như vậy.”\n“Hừm.”\nThanh Minh gật đầu như thể đã hiểu.\n“Lý do rất đơn giản.”\nHắn chỉ tay về phía Lưu Lê Tuyết.\nLưu Lê Tuyết lặng lẽ gật đầu.\nSau đó hắn lại tiếp tục chỉ về phía Bạch Thiên, Chiêu Kiệt, sau đó\nlà Nhuận Tông. Cuối cùng, ngón tay của hắn quét qua toàn bộ\ncác đệ tử Hoa Sơn một lượt.\nCuối cùng, Thanh Minh nói bằng một giọng điềm đạm.\n“Bởi vì quá yếu.”\n\nTruyện được mua và tổng hợp bởi page Hoa Sơn Tái Khởi ,\nlink https://www.facebook.com/hoasontaikhoifull\nTruyện được mua và tổng hợp bởi page Hoa Sơn Tái Khởi , link\nhttps://www.facebook.com/hoasontaikhoifull\n“…….”\nKhông gian nhất thời yên tĩnh. Gương mặt của các đệ tử trở nên\ncứng đờ.\nChỉ trong nháy mắt, bầu không khí đã thay đổi.\n“.........Ta hiểu.”\nBạch Thương lên tiếng phá vỡ sự im lặng.\nRồi hắn nhìn Thanh Minh như thể hắn vẫn chưa hiểu hết.\n“Ta biết bọn ta vẫn còn thiếu sót. Bọn ta đã không làm được quá\nnhiều trong trận chiến này. Bọn ta chỉ có thể giữ chân Vạn Nhân\nPhòng mà vùng vẫy.”\n“Chính xác.”\n“Nhưng Thanh Minh à. Chuyện gì cũng có thời điểm riêng của nó.\nVõ giả phải chuyên tâm tu luyện là điều đương nhiên, nhưng\nchẳng phải bây giờ chính là lúc chúng ta nên bàn tới một chuyện\ngì đó lớn lao hơn sao.”\n\nTruyện được mua và tổng hợp bởi page Hoa Sơn Tái Khởi ,\nlink https://www.facebook.com/hoasontaikhoifull\nTruyện được mua và tổng hợp bởi page Hoa Sơn Tái Khởi , link\nhttps://www.facebook.com/hoasontaikhoifull\nBạch Thương thở dài.\n“Ta hiểu tâm trạng của con hiện giờ, một năm….. à không, chỉ\ncần thêm nửa năm nữa thôi, vị thế của Hoa Sơn sẽ trở nên vô\ncùng vững chắc. Chẳng lẽ chúng ta lại không thể chờ thêm nửa\nnăm trong khi Tứ Bá Liên đã thỏa hiệp tới tận ba năm sao?”\n“Nửa năm?”\n“Phải, nửa năm!”\nBạch Thương nhìn thẳng vào Thanh Minh.\nHắn là người của Tái Khuynh Các, hắn đã được học về tài chính\ncủa Hoa Sơn, được học về cách thế gian xoay chuyển lợi nhuận,\nvà nắm bắt dòng chảy thương quyền của Hoa Sơn.\nVậy nên hắn biết. Hắn biết rõ hơn bất cứ ai đang ở nơi này.\nRằng Hoa Sơn đang nắm trong tay một cơ hội lớn tới mức nào.\n\nTruyện được mua và tổng hợp bởi page Hoa Sơn Tái Khởi ,\nlink https://www.facebook.com/hoasontaikhoifull\nTruyện được mua và tổng hợp bởi page Hoa Sơn Tái Khởi , link\nhttps://www.facebook.com/hoasontaikhoifull\nNếu là môn phái khác thì các đệ tử của\nhọ đã toàn tâm toàn lực xông tới nắm lấy cơ hội này rồi. Làm sao\nhắn có thể đá cơ hội ấy đi, sao hắn có thể đạp lên cơ hội ấy mà\nsống tiếp chứ?\nVậy nên hắn hoàn toàn không thể hiểu được tình hình lúc này.\n“Chờ thêm nửa năm thì có gì tốt hơn à?”\n“Con không biết nên mới hỏi đấy ư? Trước tiên là kim lực! Và\ndanh tiếng! Hơn hết là các môn phái sẽ kết minh với Hoa Sơn\ncùng Thiên Hữu Minh. Cả danh dự và địa vị nữa!”\n“…….”\n“Đây chính là cơ hội để Hoa Sơn phát triển gấp đôi! Gấp ba!\nThậm chí gấp năm! Chẳng phải đó chính là điều con mong muốn\nsao! Sao con lại muốn phong bế sơn môn sau khi chúng ta đã hy\nsinh nhiều như vậy chứ!”\nThanh Minh yên lặng nhìn Bạch Thương. Thấy thế, Bạch Thương\nngay lập tức cao giọng.\n\nTruyện được mua và tổng hợp bởi page Hoa Sơn Tái Khởi ,\nlink https://www.facebook.com/hoasontaikhoifull\nTruyện được mua và tổng hợp bởi page Hoa Sơn Tái Khởi , link\nhttps://www.facebook.com/hoasontaikhoifull\n“Và không chỉ hiện tại! Nếu chúng ta đợi\nthêm một chút nữa cho tới khi danh tiếng của Hoa Sơn cao hơn,\nthì chúng ta có thể mở môn hiệu và nhận thêm Minh Tử Bối. Khi\nấy, tất cả những đứa trẻ tài hoa đều sẽ đổ dồn về Hoa Sơn! Điều\nấy sẽ đảm bảo cho tương lai của Hoa Sơn!”\n“…….”\n“Tại sao con lại đá bỏ cơ hội lần này? Rốt cuộc là tại sao chứ?”\nTất cả cùng đồng cảm với Bạch Thương.\nAi nhìn vào cũng thấy Hoa Sơn đang không ngừng vươn lên. Chỉ\ncần họ tiếp tục phát triển theo con đường này, thì việc sánh\nngang với Cửu Phái Nhất Bang không còn là điều viển vông nữa.\n“Con hãy nói đi. Một môn phái còn cần gì ngoài võ công nữa hả?\nCon hãy nói đi!”\nMọi ánh mắt đổ dồn về phía Thanh Minh. Ánh mắt của họ chứa\nđựng quyết tâm sẽ không dễ dàng rút lui.\n\nTruyện được mua và tổng hợp bởi page Hoa Sơn Tái Khởi ,\nlink https://www.facebook.com/hoasontaikhoifull\nTruyện được mua và tổng hợp bởi page Hoa Sơn Tái Khởi , link\nhttps://www.facebook.com/hoasontaikhoifull\nThanh Minh trầm ngâm nhìn họ. Rồi\nchầm chậm cất lời.\n“Thể lực tốt. Danh tiếng cao. Mọi người cũng biết ta là kẻ mê\nnhững thứ đó hơn bất kì ai mà?”\n“Vậy thì tại sao?”\n“Sư thúc biết rồi mà vẫn hỏi ư? Chẳng phải ta đã nói rồi sao. Là\ndo mọi người quá yếu. Các sư thúc quá yếu.”\n“Ch…….”\nBạch Thương nghiến răng, bừng bừng nộ khí.\n“Con hãy trả lời cho đàng hoàng vào!”\n“Ta vừa mới nói rồi đó thôi. Các sư thúc quá yếu.”\n“Tên khốn kiếp này!”\n“Sư thúc vẫn chưa hiểu à?”\nBạch Thương nhìn dáng vẻ lạnh lùng của Thanh Minh. Bởi giọng\nnói của Thanh Minh đang ngày một nghiêm túc.\n\nTruyện được mua và tổng hợp bởi page Hoa Sơn Tái Khởi ,\nlink https://www.facebook.com/hoasontaikhoifull\nTruyện được mua và tổng hợp bởi page Hoa Sơn Tái Khởi , link\nhttps://www.facebook.com/hoasontaikhoifull\nThanh Minh từ tốn ở giữa không gian\ntĩnh lặng như tờ.\n“Lần này. May mắn đã đến với chúng ta.”\nÁnh mắt của hắn trở nên lạnh lùng.\n“Nhưng lần sau……..”\nCác đệ tử Hoa Sơn rùng mình khi chạm phải ánh mắt của hắn.\n“Chắc chắn một trong số những người đang có mặt ở đây sẽ bị\ngiết chết.”\nAi nấy đều ngậm chặt miệng.",
  "status": "ok"
}