{"index":452,"number":453,"title":"Chapter 453","source":"Hoa Sơn_/800-1000/852.pdf","body":"Truyện được mua và tổng hợp bởi page Hoa Sơn Tái Khởi ,\nlink https://www.facebook.com/hoasontaikhoifull\n\n\nChapter 852. Ta cứ thế đi tới thôi mà?\n\n(2)\n\n“......Phong bế sơn môn ư?”\n\n“Vâng.”\n\nThương Đoàn Chủ Ân Hạ Thương Đoàn Hoàng Vấn Dược kinh\n\nngạc nhìn Hoàng Tông Nghĩa.\n\n“Hoa Sơn…… phong bế sơn môn thật ư?”\n\nHoàng Vấn Dược hỏi lại như thể không thể tin được vào điều ấy.\n\nHoàng Tông Nghĩa gật đầu như thể hắn hiểu hết phản ứng của\n\nphụ thân.\n\n“Có vẻ là vậy.”\n\n“Con đang bảo ta tin vào điều ấy ư?”\n\n“........Con cũng không thể tin được chuyện đó nên đã trực tiếp tới\n\nxác nhận. Và quả thật, sơn môn của Hoa Sơn đang đóng chặt.”\n\nĐôi mắt nhăn nheo của Hoàng Vấn Dược mở to.\nTruyện được mua và tổng hợp bởi page Hoa Sơn Tái Khởi , link\nhttps://www.facebook.com/hoasontaikhoifull\n\nTruyện được mua và tổng hợp bởi page Hoa Sơn Tái Khởi ,\nlink https://www.facebook.com/hoasontaikhoifull\n\n\n“Vậy là……. Hoa Sơn đang phong bế\n\nsơn môn thực sao? Hoa Sơn ấy ư? Hoa Sơn mà ta biết á?”\n\nGiọng nói của ông ta tràn ngập sự nghi ngờ. Hoàng Tông Nghĩa\n\nnghiêm túc gật đầu.\n\n“Có vẻ như đúng là vậy ạ. Bây giờ tin đồn đã lan ra khắp thiên hạ\n\nchứ không chỉ còn ở Thiểm Tây nữa rồi.”\n\n“Vậy ư. Thế thì chắc là đúng rồi. Chắc là đúng rồi…….”\n\n“…….”\n\n“Chắc chắn là vậy rồi……”\n\nÁnh mắt của Hoàng Vấn Dược tràn ngập cảm xúc không thể diễn\n\ntả thành lời.\n\nSoàm soạp soàm soạp.\n\n“Vậy…….”\n\n2\n\nChóp chép chóp chép.\nTruyện được mua và tổng hợp bởi page Hoa Sơn Tái Khởi , link\nhttps://www.facebook.com/hoasontaikhoifull\n\nTruyện được mua và tổng hợp bởi page Hoa Sơn Tái Khởi ,\nlink https://www.facebook.com/hoasontaikhoifull\n\n\n“.......Rốt cuộc chuyện này là sao?”\n\nÔng ta run rẩy nhìn kẻ đang quét sạch bàn ăn như một cơn vũ\n\nbão.\n\nNếu Hoa Sơn thật sự phong bế sơn môn…… thì sao gã này có\n\nthể ở đây được….?5\n\n‘Hắn là quỷ à?’\n\nChóp chép chóp chép!\n\nThanh Minh bẻ một cái chân vịt lớn, nhai nhồm nhoàm sột soạt,\n\nrồi đặt bình rượu xuống cái ầm.\n\n“Khàa. Sống rồi.”\n\n“…….”\n\n“Quả nhiên đồ ăn sinh ra là để người ta ăn mà. Chẹp. Hoa Sơn\n\nphải đổi đầu bếp thôi. Nhạt nhẽo chết đi được.”\n\nHoàng Vấn Dược ngây ngốc nhìn Thanh Minh rồi mở miệng.\n\n“Này…… đạo trưởng.”\nTruyện được mua và tổng hợp bởi page Hoa Sơn Tái Khởi , link\nhttps://www.facebook.com/hoasontaikhoifull\n\nTruyện được mua và tổng hợp bởi page Hoa Sơn Tái Khởi ,\nlink https://www.facebook.com/hoasontaikhoifull\n\n\nVừa thấy ông ta run rẩy cất lời, Thanh\n\nMinh liền thản nhiên quay đầu lại như thể muốn hỏi tại sao lại gọi\n\nta.\n\n“Hả?”\n\n“Chuyện….. ta vừa nghe….. là thật sao?”\n\n“Chuyện nào? Phong bế sơn môn á hả?”\n\n“Phải. Chuyện Hoa Sơn phong bế sơn môn…….”\n\n“Đúng rồi đấy. Tại vì nhiều chuyện phiền phức quá nên bọn ta\n\nphong bế sơn môn luôn.”\n\nHoàng Vấn Dược không cần hắn phải giải thích nghi vấn khi nãy\n\nnữa.\n\n“Tại sao chứ?”\n\nÀ không…… đôi khi vẫn có người cần được giải thích.\n\n“Đạo, đạo trưởng vừa nói Hoa Sơn đã phong bế sơn môn mà,\n\nsao đạo trưởng lại tới đây được……?”\nTruyện được mua và tổng hợp bởi page Hoa Sơn Tái Khởi , link\nhttps://www.facebook.com/hoasontaikhoifull\n\nTruyện được mua và tổng hợp bởi page Hoa Sơn Tái Khởi ,\nlink https://www.facebook.com/hoasontaikhoifull\n\n\n“À, ta sao?”\n\n“Vâng.”\n\n“Ta cứ thế đi tới thôi mà?”\n\n“…….”\n\nHoàng Vấn Dược bật cười.\n\n‘Đừng cố gắng hiểu hắn làm gì.’\n\nDù sao đây cũng chẳng phải chuyện lần một lần hai….. bởi cứ\n\nmỗi khi có chuyện, là chuyện này lại lặp đi lặp lại như vậy. Nên ai\n\ncũng phải tự thích ứng thôi.\n\nThế nhưng Hoàng Tông Nghĩa vẫn chưa từ bỏ.\n\n“Nếu, nếu Hoa Sơn thực sự phong bế Hoa Sơn, thì đạo trưởng\n\nđâu được phép ra ngoài?”\n\n“Ta á?”\n\n“Phải.”\n\n\nTruyện được mua và tổng hợp bởi page Hoa Sơn Tái Khởi , link\nhttps://www.facebook.com/hoasontaikhoifull\n\nTruyện được mua và tổng hợp bởi page Hoa Sơn Tái Khởi ,\nlink https://www.facebook.com/hoasontaikhoifull\n\n\n“Tại sao?”\n\n“…….”\n\nChuyện của ngươi mà, sao lại hỏi ta? Ngươi phải trả lời cho tử tế\n\nđi chứ!\n\nThanh Minh lại đưa bình rượu lên tu ừng ực, sau khi khà một\n\ntiếng, hắn đưa tay quẹt miệng rồi mở miệng.\n\n“Hơ. Dù sao bọn ta phong bế sơn môn cũng có phải vì đã gây ra\n\nchuyện gì đâu. Bọn ta phong bế sơn môn là để mấy kẻ phiền\n\nphức không tìm tới nữa thôi, tại sao ta lại không thể ra ngoài?”\n\n“......Ơ, ơ không. Nhưng dù sao cũng là phong bế sơn môn.”\n\n“Ầy, ai cũng vậy thôi. Làm gì có mấy kẻ tuân thủ nghiêm ngặt\n\nmôn luật lúc phong bế sơn môn chứ. Kiểu gì trong lúc đang\n\nphong bế sơn môn, mấy tên Tông Nam hay Võ Đang khốn kiếp\n\ncũng lén lút mặc dạ hành y lẻn ra ngoài uống rượu vào ban đêm.\n\nTa đảm bảo đó, ta đảm bảo luôn.”\n\n\nTruyện được mua và tổng hợp bởi page Hoa Sơn Tái Khởi , link\nhttps://www.facebook.com/hoasontaikhoifull\n\nTruyện được mua và tổng hợp bởi page Hoa Sơn Tái Khởi ,\nlink https://www.facebook.com/hoasontaikhoifull\n\n\n“…….”\n\n“Vậy nên ngài hãy bỏ qua mấy chuyện nhỏ nhặt đó đi.”\n\n“.......Vâng.”\n\nPhải rồi. Thà rằng cứ bỏ qua đi cho tâm trạng thoải mái.\n\n“Dù sao mọi chuyện cũng đã vậy rồi, ta mong các ngài sẽ quản lý\n\nthật tốt công việc ở Hoa Âm và cả việc con đường mậu dịch với\n\nBắc Hải. Phía Đường Môn sẽ đứng ra giúp đỡ nếu Ân Hạ Tiêu\n\nHành xảy ra chuyện, nên nếu có chuyện gì, các vị cứ yêu cầu\n\nĐường Môn giúp đỡ là được.”\n\n“Vâng.”\n\n“Và khi tiếp tế lương thực cho Hoa Sơn, các ngài nhớ mang thêm\n\nthật thật thật nhiều thịt nhé…… và, ừm……. ừm……..”\n\nThanh Minh ngập ngừng, cố tình kéo dài giọng, hướng ánh mắt\n\nnhư muốn nói ‘Ta có nhất thiết phải nói ra điều này không?’ về\n\nphía Hoàng Tông Nghĩa. Hoàng Tông Nghĩa thảm thương cất lời.\n\nTruyện được mua và tổng hợp bởi page Hoa Sơn Tái Khởi , link\nhttps://www.facebook.com/hoasontaikhoifull\n\nTruyện được mua và tổng hợp bởi page Hoa Sơn Tái Khởi ,\nlink https://www.facebook.com/hoasontaikhoifull\n\n\n“.......Ta sẽ cất đầy rượu ở nơi bí mật\n\nnhư thường lệ.”\n\n“Ha. Ha.. Ha. Ha. Cũng không tới mức đó đâu, mặc dù không\n\nphải là ta không thể ra ngoài vì đang phong bế sơn môn, aigu.\n\nRượu sẽ hỏng mất thôi, hỏng mất thôi!”\n\n“.......Vậy ta cho ít lại nhé?”\n\n“Hả?”\n\n“À, à không, tại đạo trưởng nói rượu sẽ bị hỏng nên……”\n\n“Hảa?”\n\n“.......Ta sẽ chuẩn bị thật nhiều.”\n\n“Khừ. Nếu ngài cứ khăng khăng như vậy thì ta cũng đành chịu\n\nthôi.”\n\nThanh Minh nhún vai rồi lại cất lời.\n\n“À, phải rồi, sẽ có đồ từ Đường Môn chuyển tới đấy. Cả đồ của\n\nBắc Hải gửi cho Hoa Sơn nữa. Nếu chúng tới thì các vị hãy\nTruyện được mua và tổng hợp bởi page Hoa Sơn Tái Khởi , link\nhttps://www.facebook.com/hoasontaikhoifull\n\nTruyện được mua và tổng hợp bởi page Hoa Sơn Tái Khởi ,\nlink https://www.facebook.com/hoasontaikhoifull\n\n\nchuyển tới Hoa Sơn giúp ta nhé, bất kể\n\nHoa Sơn có còn đang phong bế sơn môn hay không. Bởi vì Ân\n\nHạ Thương Đoàn vẫn có thể tiến vào mà.”\n\n“Ta sẽ làm vậy.”\n\nSau khi dặn dò mọi chuyện, hắn thở phào nhẹ nhõm.\n\n“Mặc dù ta rất muốn nói sẽ thường xuyên ghé chơi, nhưng thực\n\nra, đây là lần cuối rồi. Sẽ rất khó để ta ghé lại cho tới khi kết thúc\n\nphong bế sơn môn.”\n\n“Ừmmm.”\n\n“Ta đã rất lo lắng vì sẽ có nhiều chuyện xảy ra, nhưng ta tin các vị\n\nsẽ làm tốt.”\n\nHoàng Vấn Dược mỉm cười.\n\n“Đạo trưởng không cần quá lo lắng đâu.”\n\n“Nhưng mà…….”\n\n\n\nTruyện được mua và tổng hợp bởi page Hoa Sơn Tái Khởi , link\nhttps://www.facebook.com/hoasontaikhoifull\n\nTruyện được mua và tổng hợp bởi page Hoa Sơn Tái Khởi ,\nlink https://www.facebook.com/hoasontaikhoifull\n\n\nThanh Minh nhìn Hoàng Vấn Dược như\n\nthể ông ta là một người vô cùng thần kì.\n\n“Sao ngài không hỏi tại sao bọn ta lại phong bế sơn môn? Hình\n\nnhư bình thường ai cũng thắc mắc chuyện đó mà nhỉ.”\n\nHoàng Vấn Dược lặng lẽ lắc đầu.\n\n“Người như ta, cho dù nghe cũng không hiểu. Làm sao một\n\nngười theo đuổi Lợi (利) như ta có thể hiểu được tâm tình của\n\nnhững người truy cầu Đạo (道) chứ.”\n\n\n“…….”\n\n“Ta chỉ cần biết rằng đạo trưởng có Đại Ý (大意) nên mới làm\n\nvậy.”\n\n“Làm gì có chuyện đó.”\n\nHoàng Vấn Dược mỉm cười nhìn Thanh Minh ngại ngùng gãi đầu.\n\n\nTruyện được mua và tổng hợp bởi page Hoa Sơn Tái Khởi , link\nhttps://www.facebook.com/hoasontaikhoifull\n\nTruyện được mua và tổng hợp bởi page Hoa Sơn Tái Khởi ,\nlink https://www.facebook.com/hoasontaikhoifull\n\n\n“Dù sao thì ta cũng sẽ xử lý thật tốt mọi\n\nchuyện để không xảy ra vấn đề gì. Bọn ta cũng sẽ hợp tác với\n\nHoa Ảnh Môn ở Tây An để nâng cao số lượng tục gia môn phái.”\n\n“À, đúng rồi nhỉ. Chuyện đó ta cũng phải nhờ ngài nữa rồi.”\n\n“Đạo trưởng không cần quan tâm những chuyện nhỏ nhặt như\n\nvậy đâu. Đạo trưởng chỉ cần quán triệt tinh thần là được. Còn\n\nnhững người như bọn ta sẽ lo liệu mọi chuyện phía sau.”\n\n“Nhân tiện cũng kiếm được tiền luôn phải không?”\n\n“Tất nhiên rồi, tất nhiên rồi. Đạo trưởng biết rõ thật đấy. Hahaha.”\n\nHoàng Vấn Dược cười như thể ông ta đang rất vui.\n\n“Đạo trưởng.”\n\n“Vâng?”\n\n“Từ sau khi đạo trưởng xuất hiện, không chỉ Tây An và Hoa Âm,\n\nmà cả toàn bộ Thiểm Tây đều tràn ngập sinh khí. Đặc biệt là lòng\n\n\n\nTruyện được mua và tổng hợp bởi page Hoa Sơn Tái Khởi , link\nhttps://www.facebook.com/hoasontaikhoifull\n\nTruyện được mua và tổng hợp bởi page Hoa Sơn Tái Khởi ,\nlink https://www.facebook.com/hoasontaikhoifull\n\n\ntự hào của người dân Hoa Âm, quả thực\n\nkhông thể diễn tả thành lời.”\n\n“Ầy. Ta có làm gì đâu.”\n\n“Và cũng nhờ đạo trưởng mà Ân Hạ Thương Đoàn như được\n\nchắp thêm đôi cánh.”\n\nHoàng Vấn Dược trang trọng cúi đầu về phía Thanh Minh.\n\n“Đa tạ đạo trưởng.”\n\n“Ấy, tự dưng ngài làm gì thế!”\n\nThanh Minh giật mình vội vã đỡ Hoàng Vấn Dược. Hoàng Vấn\n\nDược mỉm cười gật đầu.\n\n“Ta đã rất muốn một lần được gửi lời cảm ơn tới đạo trưởng. Vì\n\nta chưa bao giờ bày tỏ lòng biết ơn chân thành của mình tới đạo\n\ntrưởng cả.”\n\n“Cảm ơn gì chứ. Quan hệ giữa chúng ta đâu cần ngài phải làm\n\nvậy.”\n\nTruyện được mua và tổng hợp bởi page Hoa Sơn Tái Khởi , link\nhttps://www.facebook.com/hoasontaikhoifull\n\nTruyện được mua và tổng hợp bởi page Hoa Sơn Tái Khởi ,\nlink https://www.facebook.com/hoasontaikhoifull\n\n\nHoàng Vấn Dược mỉm cười nhìn Thanh\n\nMinh.\n\nNgẫm lại thì mối quan hệ của họ cũng chẳng phải một mối nhân\n\nduyên lâu đời. Bọn họ mới chỉ quen nhau vài năm. Thế nhưng,\n\nnhững năm đó đã cứu mạng Hoàng Vấn Dược, thay đổi cuộc\n\nsống của ông ta, thậm chí là cả tương lai của Ân Hạ Thương\n\nĐoàn.\n\nTất cả đều nhờ sự xuất hiện của người đó.\n\nThanh Minh gượng gạo đón nhận ánh mắt ấm áp của Hoàng Vấn\n\nDược.\n\n“Dù sao thì cũng nhờ các vị cả nhé. Đặc biệt là việc quản lý Tây\n\nAn. Biết đâu chừng trong thời gian ta vắng mặt, lũ Tông Nam\n\nkhốn kiếp sẽ kết thúc phong bế sơn môn đến gây loạn.”\n\n“Tất nhiên rồi. Bây giờ sức mạnh của Ân Hạ Thương Đoàn không\n\nhề yếu chút nào. Ít nhất thì ta sẽ đảm bảo cho các môn phái tục\n\n\nTruyện được mua và tổng hợp bởi page Hoa Sơn Tái Khởi , link\nhttps://www.facebook.com/hoasontaikhoifull\n\nTruyện được mua và tổng hợp bởi page Hoa Sơn Tái Khởi ,\nlink https://www.facebook.com/hoasontaikhoifull\n\n\ngia của Hoa Sơn ở Tây An và các môn\n\nphái liên quan tới Hoa Sơn sẽ không gặp phải bất lợi gì.”\n\n“Vâng. Như vậy là đủ rồi. Vậy ta xin phép.”\n\nThanh Minh cầm bình rượu đi về phía cửa. Thế nhưng, ngay khi\n\nvừa nắm lấy tay cửa, hắn liền ngập ngừng.\n\n“Chuyện đó……”\n\n“Vâng, đạo trưởng.”\n\n“Ngài không cần lo đâu. Bởi Hoa Sơn và Ân Hạ Thương Đoàn là\n\nbằng hữu mà.”\n\nHoàng Tông Nghĩa nghiêng đầu trước lời nói đột ngột ấy. Thế\n\nnhưng, Hoàng Vấn Dược lại gật đầu như thể ông ta hiểu được ý\n\nThanh Minh.\n\n“Nếu đạo trưởng đã nói vậy thì ta không còn mong đợi gì thêm\n\nnữa.”\n\n“Vâng, vậy ta xin phép.”\n\nTruyện được mua và tổng hợp bởi page Hoa Sơn Tái Khởi , link\nhttps://www.facebook.com/hoasontaikhoifull\n\nTruyện được mua và tổng hợp bởi page Hoa Sơn Tái Khởi ,\nlink https://www.facebook.com/hoasontaikhoifull\n\n\nThanh Minh nhìn Hoàng Vấn Dược, mỉm\n\ncười rồi mở cửa bước ra ngoài.\n\nCạch.\n\nCánh cửa đóng lại, Hoàng Tông Nghĩa cau mày như thể hắn vẫn\n\nchưa hiểu chuyện gì.\n\n“........Tại sao Thanh Minh đạo trưởng lại tới đây vậy ạ?”\n\n“Tại sao ư…….”\n\n“Thanh Minh đạo trưởng đã định nói gì đó, nhưng chẳng phải là\n\nnó không có ý nghĩa gì sao? Mặc dù Thanh Minh đạo trưởng tới\n\nđây giao phó công việc cho chúng ta, nhưng dù ngài ấy không\n\ntới, thì chúng ta cũng vẫn làm mà. Thanh Minh đạo trưởng đâu\n\ncần thiết phải ra ngoài trong lúc phong bế sơn môn…….”\n\n“Tông Nghĩa này. Con người ấy mà……”\n\n“Vâng, thưa phụ thân.”\n\n\nTruyện được mua và tổng hợp bởi page Hoa Sơn Tái Khởi , link\nhttps://www.facebook.com/hoasontaikhoifull\n\nTruyện được mua và tổng hợp bởi page Hoa Sơn Tái Khởi ,\nlink https://www.facebook.com/hoasontaikhoifull\n\n\nThấy Hoàng Vấn Dược nói bằng một\n\ngiọng nghiêm túc, Hoàng Tông Nghĩa vội vàng chỉnh lại tư thế.\n\n“So với vẻ bề ngoài thì Chân Ý (眞意) chứa đựng bên trong quan\n\ntrọng hơn. Đã là thương nhân, con phải biết đọc được ẩn ý trong\n\ntừng lời nói của Thanh Minh đạo trưởng chứ.”\n\n“…….”\n\n“Thanh Minh đạo trưởng tới đây chỉ để chào hỏi thôi.”\n\n“Chào hỏi? Ý người là Thanh Minh đạo trưởng tới để chào tạm\n\nbiệt chúng ta vì Hoa Sơn phong bế sơn môn sao?”\n\n“Không phải.”\n\nHoàng Vấn Dược lắc đầu. Nói bằng một giọng bình tĩnh.\n\n“Thanh Minh đạo trưởng tới để tiễn biệt một người mà ngài ấy sẽ\n\nkhông bao giờ gặp lại nữa.”\n\n“.......Phụ, phụ thân?”\n\nHoàng Vấn Dược mỉm cười nói tiếp.\nTruyện được mua và tổng hợp bởi page Hoa Sơn Tái Khởi , link\nhttps://www.facebook.com/hoasontaikhoifull\n\nTruyện được mua và tổng hợp bởi page Hoa Sơn Tái Khởi ,\nlink https://www.facebook.com/hoasontaikhoifull\n\n\n“Chẳng phải Thanh Minh đạo trưởng là\n\nngười có tấm lòng rất ấm áp sao? Có lẽ trong lòng ngài ấy có\n\nvướng mắc khi Hoa Sơn phong bế sơn môn. Dẫu sao bây giờ lão\n\ngià này không còn là người quan trọng đến vậy đối với Hoa Sơn\n\nnữa rồi…….”\n\nHoàng Vấn Dược biết.\n\nCó lẽ ông ta sẽ không thể đợi được tới lúc Hoa Sơn kết thúc\n\nphong bế sơn môn. Bởi vì ông ta đã sớm chạm tới thiên thu.\n\nVà có lẽ Thanh Minh cũng đã đoán ra điều ấy.\n\n“Ta không còn gì hối tiếc nữa. Suy cho cùng thì ta cũng không thể\n\ntránh khỏi số phận. Chẳng phải cũng nhờ đạo trưởng ấy đã cứu\n\nmạng mà ta mới có thể chứng kiến thêm nhiều chuyện nằm ngoài\n\nsức tưởng tượng nữa sao.”\n\n“Phụ thân……”\n\n“Nếu ta còn điều lo lắng, thì đó chỉ là con và thương đoàn thôi. Có\n\nlẽ Thanh Minh đạo trưởng đã đoán ra. Ta sẽ không thể yên lòng\nTruyện được mua và tổng hợp bởi page Hoa Sơn Tái Khởi , link\nhttps://www.facebook.com/hoasontaikhoifull\n\nTruyện được mua và tổng hợp bởi page Hoa Sơn Tái Khởi ,\nlink https://www.facebook.com/hoasontaikhoifull\n\n\nvì lo lắng cho con và thương đoàn nếu\n\nnhư ta nhắm mắt xuôi tay trong lúc Hoa Sơn phong bế sơn môn.\n\nVậy nên ngài ấy mới cố tình tìm đến để nhắc nhở ta không cần lo\n\nlắng.”\n\nNói xong, Hoàng Vấn Dược chầm chậm nhắm mắt.\n\n‘Đạo Khí (道器) không phải thứ gì xa lạ.’\n\n\nÔng ta biết.\n\nTuy bề ngoài Thanh Minh có chút ngỗ nghịch, nhưng nội tâm hắn\n\nlại là một người vô cùng ấm áp.\n\n“Đạo trưởng sẽ phải lo lắng nhiều lắm đây.”\n\n“........Thanh Minh đạo trưởng sao ạ?”\n\n“Một cuộc hỗn loạn sẽ xảy ra. Thế gian sẽ thay đổi.”\n\n“…….”\n\n“Và trong thế giới tàn nhẫn đó, con người tình cảm ấy sẽ phải\n\nchịu vô vàn tổn thương.”\nTruyện được mua và tổng hợp bởi page Hoa Sơn Tái Khởi , link\nhttps://www.facebook.com/hoasontaikhoifull\n\nTruyện được mua và tổng hợp bởi page Hoa Sơn Tái Khởi ,\nlink https://www.facebook.com/hoasontaikhoifull\n\n\nHoàng Vấn Dược khẽ thở dài.\n\n“Tông Nghĩa. Làm người mà không biết ơn nghĩa thì cũng chẳng\n\nkhác nào thú vật.”\n\n“Vâng.”\n\n“Con hãy giúp đỡ ngài ấy và Hoa Sơn, không chỉ với tư cách là\n\nThương Đoàn Chủ Ân Hạ Thương Đoàn, mà còn với tư cách là\n\nmột con người.”\n\n“.......Con xin khắc cốt ghi tâm.”\n\n“Được. Vậy là được rồi.”\n\nHoàng Vấn Dược mỉm cười.\n\nÔng ta có chút tiếc nuối khi không thể tận mắt chứng kiến cảnh\n\ntượng Hoa Sơn và Ân Hạ Thương Đoàn đứng trên đỉnh cao thiên\n\nhạ. Tuy nhiên, ông ta cũng chẳng luyến tiếc quá nhiều bởi dù\n\nkhông tận mắt chứng kiến, ông ta vẫn có thể đoán được ra cảnh\n\ntượng ấy.\n\nTruyện được mua và tổng hợp bởi page Hoa Sơn Tái Khởi , link\nhttps://www.facebook.com/hoasontaikhoifull\n\nTruyện được mua và tổng hợp bởi page Hoa Sơn Tái Khởi ,\nlink https://www.facebook.com/hoasontaikhoifull\n\n\n“Đại bằng phải chờ cả ngàn năm mới có\n\nthể một lần cất cánh. Ta thật kì vọng không biết sau khi kết thúc\n\nphong bế sơn môn, Hoa Sơn sẽ bay cao tới mức nào.”\n\n“Sẽ như vậy ạ, thưa phụ thân.”\n\n“Hahaha. Nhưng trước lúc ấy, chúng ta phải hoàn thành công\n\nviệc mà Thanh Minh đạo trưởng giao phó. Sẽ bận rộn lắm đây.\n\nMau đi thôi.”\n\n“Vâng, phụ thân.”\n\nHoàng Vấn Dược mở cửa bước ra khỏi phòng, nhìn về đại môn\n\nThanh Minh vừa bước qua, rồi hướng mắt về Hoa Sơn ở nơi cao.\n\n“Tới một lúc nào đó….. hoa nhất định sẽ nở.”\n\nDẫu vậy, Hoàng Vấn Dược vẫn mong ông ta có thể vui vẻ ngắm\n\nnhìn vào ngày hoa lại nở.\n\n“Bảo trọng nhé, đạo trưởng.”\n\n\nTruyện được mua và tổng hợp bởi page Hoa Sơn Tái Khởi , link\nhttps://www.facebook.com/hoasontaikhoifull\n\nTruyện được mua và tổng hợp bởi page Hoa Sơn Tái Khởi ,\nlink https://www.facebook.com/hoasontaikhoifull\n\n\nNụ cười nở trên khóe môi đã in hằn\n\nnhiều dấu ấn theo năm tháng của Hoàng Vấn Dược.\n\n\nTruyện được mua và tổng hợp bởi page Hoa Sơn Tái Khởi , link\nhttps://www.facebook.com/hoasontaikhoifull"}