{
  "index": 1290,
  "number": 1761,
  "rangeEnd": null,
  "title": "Chapter 1761. Đó là lý do ta ở đây. (1)",
  "source": "Hoa Sơn_/1700 - 2000/1761.docx",
  "body": "Chapter 1761. Đó là lý do ta ở đây. (1)\n\n\nNhững ngón tay thon dài và trắng nõn lướt qua bàn cờ. Bàn cờ phía dưới là một loại cao cấp, trông rất sang trọng, thật không phù hợp với quang cảnh chiến trường lúc này.\n\n\n“Hừm.”\n\n\nHắn muốn chặn đường đối phương ngay lập tức, nhưng suy nghĩ một hồi rồi lại thôi. Sau đó, có lẽ vì không hài lòng với kế hoạch ban đầu nên hắn đã đặt cờ ở một vị trí hoàn toàn khác so với dự định.\n\n\nÁnh mắt hắn nhìn về phía bàn cờ cực kỳ nghiêm túc, nhưng trong giọng nói của hắn lại phát ra ý trêu đùa.\n\n\n“Thật kỳ lạ. Ngươi mà lại đi nước đi như thế này sao?”\n\n\nTrường Nhất Tiếu liếc nhìn Hỗ Gia Danh lúc này đang ngồi ở phía đối diện. Hỗ Gia Danh không quan tâm đến điều đó, hắn chỉ nhìn chăm chăm vào bàn cờ.\n\n\n“Việc này cũng đâu có gì kỳ lạ. Thuộc hạ vốn đã chơi như thế này từ trước đến giờ rồi.”\n\n\n“Ừ. Chắc là do ngươi buồn ngủ thôi.”\n\n\nĐã từng có một thời kỳ như vậy.\n\n\nThời kỳ cực kỳ căng thẳng nhưng đồng thời cũng vô cùng nhàm chán. Khoảng thời gian hắn phải lang thang một mình trong những con hẻm nhỏ bẩn thỉu và ngâm mình trong nước bùn.\n\n\nHỗ Gia Danh cắt quân.\n\n\nHắn đặt quân cờ đen vào một điểm trên bàn cờ rồi nói.\n\n\n“Có thể đó là một sai lầm.”\n\n\n“Sai lầm sao?”\n\n\n“Thủ đàm (手談).... Cờ vây cũng chính là một quân tử chi lược, thuộc hạ đã học được điều đó từ sư phụ của mình.”\n\n\n“Thật là nhảm nhí.”\n\n\n“Nhưng Bang Chủ...... Không, Minh Chủ đã không thể thắng. Mặc dù người dạy Minh Chủ chơi cờ là thuộc hạ.”\n\n\nTrường Nhất Tiếu cười nhạt.\n\n\n“Chậc chậc chậc. Nếu ngươi để tâm đến thế thì phải nhẹ tay với bổn quân thôi chứ.”\n\n\n“Bản thân thuộc hạ cảm thấy khó chịu là điều dễ hiểu.”\n\n\nHỗ Gia Danh nói tiếp như thể hoàn toàn không quan tâm gì đến lời nói của Trường Nhất Tiếu.\n\n\n“Chơi cờ là để trò chuyện cùng đối phương, cũng như là nhìn vào gương để soi chiếu bản thân mình. Vậy nên khi chơi, phải biết nhẫn nhịn và tiến về phía trước, không chỉ là một bước phía trước mà phải còn xa hơn thế nữa. Nhưng...... khi chơi cùng Minh Chủ...... thuộc hạ lại không thể như vậy.”\n\n\nCạch.\n\n\nTrường Nhất Tiếu đặt quân cờ trắng của mình xuống.\n\n\nHỗ Gia Danh im lặng nhìn quân cờ của Trường Nhất Tiếu đang đánh vào điểm yếu của mình.\n\n\n“Tính cách của Minh Chủ quá tự do. Mặc dù thuộc hạ là người dạy cho Minh Chủ chơi cờ, nhưng Minh Chủ luôn đi những nước cờ mà thuộc hạ không thể hiểu được.”\n\n\n“Hừm, bổn quân không biết nữa...... chẳng phải do ngươi quá thật thà hay sao?”\n\n\nHỗ Gia Danh đáp “cũng có thể như vậy” đầy vẻ giễu cợt rồi tiếp tục chặn đường của Trường Nhất Tiếu.\n\n\nPhản ứng trái với mong đợi khiến Trường Nhất Tiếu tụt cả hứng. Hắn tựa lưng vào ghế.\n\n\n“Vậy nên trong lúc này mà ngươi lại muốn hồi tưởng về quá khứ sao?”\n\n\nÁnh mắt của Trường Nhất Tiếu lóe lên.\n\n\nThực ra hắn chơi cờ vây là do Hỗ Gia Danh yêu cầu, bằng không, hắn cũng chẳng thiết chơi để làm gì. Bởi vì bây giờ đã không còn thời gian dư dả.\n\n\n“Gia Danh.”\n\n\n“Tới lượt Minh Chủ rồi.”\n\n\nHỗ Gia Danh vẫn điềm tĩnh.\n\n\nTrường Nhất Tiếu không phải kiểu người lãng phí thời gian như thế này.\n\n\nHỗ Gia Danh, người đồng hành với hắn đã lâu cũng thế. Có khi Hỗ Gia Danh còn nghiêm chỉnh tận dụng thời gian hơn cả Trường Nhất Tiếu.\n\n\nTrường Nhất Tiếu thở dài.\n\n\n“Được rồi, để bổn quân xem việc này rốt cuộc có ý nghĩa là gì nào.”\n\n\nHắn ngồi thẳng thớm lại rồi bắt đầu tập trung cực độ.\n\n\nSự im lặng bao trùm lấy hai người. Chỉ có âm thanh của những quân cờ được đặt xuống bàn.\n\n\nĐiều đáng ngạc nhiên là người lên tiếng phá vỡ sự im lặng đầu tiên lại là Hỗ Gia Danh.\n\n\n“Nhưng gần đây, suy nghĩ của thuộc hạ đã thay đổi một chút.”\n\n\n“Ý của ngươi là gì?”\n\n\n“Khi thuộc hạ cố gắng quan sát, thuộc hạ lại chẳng thể thấy được gì. Có nói chuyện thì cũng không thể hiểu được. Người ta nói thủ đàm cũng chỉ là một cái cớ cho những người cao quý cần việc gì đó làm để giết thời gian mà thôi.”\n\n\n“....”\n\n\n“Nghĩ lại thì điều đó không sai.”\n\n\n“Hừm, đang đối đầu với bổn quân mà ngươi nói nhiều thật.”\n\n\nCách.\n\n\nQuân cờ của Trường Nhất Tiếu đặt giữa thế trận của Hỗ Gia Danh.\n\n\nMột quân cờ trắng tinh được bao quanh bởi những quân cờ màu đen. Đó quả thực là một nước đi liều lĩnh.\n\n\nNhưng vẻ mặt của Hỗ Gia Danh lại cứng lại.\n\n\nBởi hắn nhận ra, nước đi này của Trường Nhất Tiếu có thể kéo “đại mã (大馬)” của hắn xuống địa ngục.\n\n\n“Ngươi thấy thế nào?”\n\n\nHỗ Gia Danh im lặng không đáp lời, hắn lẳng lặng xây thế phòng thủ.\n\n\nNhưng Trường Nhất Tiếu càng đi nhiều nước, tình hình của Hỗ Gia Danh càng trở nên khó khăn.\n\n\nGiữa lãnh thổ của Hỗ Gia Danh, những quân cờ đen đang bao vây lấy quân cờ màu trắng.\n\n\nTrường Nhất Tiếu cười nhạt.\n\n\n“Ôi chao...... tình hình của ngươi có vẻ căng thẳng rồi đấy, ngươi sẽ lùi lại mấy bước đây?”\n\n\nHỗ Gia Danh lặng lẽ nhìn vào bàn cờ rồi ngẩng lên nhìn Trường Nhất Tiếu.\n\n\n“Minh Chủ nghĩ sao?”\n\n\n“Hửm? Chuyện gì?”\n\n\n“Minh Chủ có thể thấy được suy nghĩ của thuộc hạ lúc này không?”\n\n\nTrường Nhất Tiếu hơi nheo mắt lại. Hỗ Gia Danh lắc đầu.\n\n\n“Minh Chủ không thấy được.”\n\n\n“....”\n\n\n“Trước đây, mỗi lần nhìn vào Minh Chủ, thuộc hạ đều cảm giác rằng bản thân đang bị lột trần hết mọi thứ. Thuộc hạ có không thể hiện suy nghĩ của mình ra ngoài thì Minh Chủ cũng có thể nhìn thấu. Nhưng bây giờ thì không như vậy nữa.”\n\n\nVẻ mặt của Trường Nhất Tiếu thoáng cứng đờ.\n\n\n“.... Rốt cuộc là ngươi muốn nói gì?”\n\n\n“Minh Chủ từng là một người như vậy. Một người có thể làm những việc quá sức tưởng tượng của người bình thường một cách thản nhiên. Dù là trên chiến trường hay trên bàn cờ đều như vậy.”\n\n\nCạch.\n\n\nHỗ Gia Danh lại thờ ơ đặt quân cờ xuống. Vẻ mặt của Trường Nhất Tiếu có chút biến đổi. Nụ cười nhạt thoáng qua gương mặt cứng đờ của hắn rồi biến thành một thứ gì đó trông thật ghê rợn.\n\n\n“Hờ......”\n\n\nThế cục trên bàn cờ đã thay đổi.\n\n\nTrường Nhất Tiếu vẫn có thể bắt được đại mã của Hỗ Gia Danh. Nhưng một ngôi nhà lớn đã được dựng lên ở một nơi không liên quan đến đại mã từ lúc nào.\n\n\nNhưng quân cờ xung quanh như đang vùng vẫy để sống sót.\n\n\nTrong trường hợp này, Trường Nhất Tiếu dù có bắt được đại mã thì cũng không thể thắng.\n\n\n‘Mồi nhử sao?’\n\n\nQuân đại mã kia chính là mồi nhử ư?\n\n\nĐiều khiến Trường Nhất Tiếu cảm thấy bàng hoàng thậm chí là tức giận lúc này chính là việc hắn đã thua bằng một thứ mà hắn không bao giờ ngờ tới.\n\n\n“Gia Danh......”\n\n\n“Minh Chủ có nhớ không?”\n\n\nHỗ Gia Danh kiên định nói.\n\n\n“Trước đây...... chúng ta có chơi cờ vây cùng nhau một vài lần. Nhưng lúc đó, quan điểm của chúng ta không giống nhau.”\n\n\n“....”\n\n\nHắn nhớ.\n\n\nBởi vì trước đây, người vứt bỏ con đại mã và xây dựng thế lực ở bên ngoài chính là Trường Nhất Tiếu.\n\n\nVà hiện tại hắn đã bị mắc kẹt bởi thủ pháp mà hắn đã từng làm trong quá khứ.\n\n\n“Khi đó, thuộc hạ khá sốc. Bởi đưa đại mã làm mồi nhử cho kẻ thù và biến một khu vực mới thành lãnh thổ của riêng mình không phải là một hành vi có trong cờ vây, ít nhất theo thuộc hạ biết là như vậy. Nhưng có một lý do khác khiến thuộc hạ ngạc nhiên với cách chơi này. Việc sử dụng đại mã mà chúng ta đã dày công xây dựng không phải việc dễ dàng gì. Với người bình thường thì là như thế.”\n\n\nÁnh mắt của Hỗ Gia Danh trở nên lạnh lùng.\n\n\n“Nhưng ít nhất vào thời điểm đó, Minh Chủ không bận tâm đến việc đó. Minh Chủ là một người sử dụng bất cứ thứ mình có nếu nó hữu dụng và cũng có thể vứt bỏ đi những thứ không cần thiết. Minh Chủ là một người có thể xé toạc cánh tay của chính mình để đánh bại kẻ thù.”\n\n\n“....”\n\n\n“Nhưng bây giờ, Minh Chủ không thể buông bỏ những gì mình đang cầm trong tay. Vậy nên...... Minh Chủ sẽ phải gánh chịu hậu quả của những việc làm mà Minh Chủ đã làm trong quá khứ.”\n\n\n“Gia Danh.”\n\n\n“Minh Chủ có thấy vui không?”\n\n\n“....”\n\n\n“Thời điểm đó, đối với Minh Chủ, mọi thứ chỉ là trò tiêu khiển. Có được hay đánh mất thứ gì đó chẳng quá quan trọng với Minh Chủ. Nhưng bây giờ thì sao? Minh Chủ có đang hạnh phúc không?”\n\n\n“Đủ rồi.”\n\n\n“Hay là bây giờ Minh Chủ đã dần cảm thấy nặng nề? Minh Chủ không dám hành động vì sợ chỉ một thất bại thì mọi thứ có thể bị cướp đi mất.”\n\n\n“Ngươi hơi quá rồi đấy. Người đừng ỷ......”\n\n\n“Thuộc hạ rất tò mò. Nếu như Minh Chủ từng lang thang ở con hẻm ở Quý Châu thấy được Minh Chủ của hiện tại thì......”\n\n\nRầm!\n\n\nBàn cờ được đặt giữa hai người bay lên không trung rồi rơi xuống sàn.\n\n\nLạch cạch.\n\n\nNhững quân cờ rơi xuống mặt sàn như mưa. Trường Nhất Tiếu từ từ rút tay về.\n\n\nHắn nở một nụ cười đầy rùng rợn.\n\n\n“Hắn sẽ nhìn bổn quân như một con lợn ăn no phình bụng rồi nằm lăn ra đó chứ không phải là một con người...... ý ngươi là vậy đúng chứ?”\n\n\nThay vì trả lời, Hỗ Gia Danh lại đứng dậy. Hắn lặng lẽ nhặt những quân cờ đang rơi trên sàn.\n\n\n“Hỗ Gia Danh.”\n\n\n“Chúng đã lập trận ở Võ Đang. Và có lẽ Minh Chủ do dự cũng là vì chúng ta khó mà đối phó với khi chúng đang lập trận ở đó.”\n\n\nKhóe miệng của Trường Nhất Tiếu khẽ giật.\n\n\n“Thì sao?”\n\n\n“Kiên nhẫn và kỹ năng thực chiến là hai thứ hoàn toàn khác nhau. Vậy nên chúng ta nên kéo chúng ra khỏi đó thay vì chờ đợi.”\n\n\n“Lôi kéo chúng......”\n\n\nTrường Nhất Tiếu gõ đầu ngón tay vào đầu gối.\n\n\n“Thuộc hạ không muốn bàn cãi gì về mỹ học của Minh Chủ. Việc những kẻ ngốc chen vào cuộc chiến này mà không có lý do cũng không hẳn là sai. Nhưng mà......”\n\n\nHỗ Gia Danh nhìn thẳng vào Trường Nhất Tiếu.\n\n\n“Chẳng phải Minh Chủ đã nói trong chiến tranh, mỹ học cũng chẳng có gì quan trọng sao?”\n\n\nĐôi mắt của Trường Nhất Tiếu dao động. Hắn giải phóng sát khí như thể muốn chém bay đầu Hỗ Gia Danh ngay lập tức.\n\n\nNhưng Hỗ Gia Danh vẫn rất thản nhiên. Như thể mạng sống của hắn chẳng có gì quan trọng.\n\n\n“Xin Minh Chủ hãy ra lệnh...... Thuộc hạ sẽ chém đầu từng thường dân để dụ chúng ra ngoài. Nếu Minh Chủ không ra lệnh thì xin hãy trao lại quyền hạn cho thuộc hạ. Sau đó......”\n\n\nMột giọng nói trầm thấp nhưng đầy nghiêm túc và trịnh trọng vàng lên.\n\n\n“Thuộc hạ sẽ dâng hiến Trung Nguyên này cho Minh Chủ.”\n\n\nTrường Nhất Tiếu rơi vào im lặng.\n\n\n“Minh Chủ.”\n\n\n“Cho dù là quá khứ, hiện tại hay tương lai......”\n\n\n“....”\n\n\n“Thì cũng chỉ có ngươi mới có thể dùng những lời lẽ như vậy để nói trước mặt bổn quân.”\n\n\nHỗ Gia Danh gật đầu như thể đó là một sự thật cực kỳ hiển nhiên.\n\n\n“Đó là lý do tại sao thuộc hạ lại ở đây.”\n\n\n“Hầy......”\n\n\nTrường Nhất Tiếu dựa lưng vào ghế rồi thở dài.\n\n\n“Được rồi, ngươi muốn làm gì thì làm. Nhưng phải đảm bảo gặp hái được thành quả. Biết chưa?”\n\n\n“Thuộc hạ sẵn sàng hy sinh cả mạng sống này cho Minh Chủ.”\n\n\nHỗ Gia Danh cúi đầu rồi quay người đi.\n\n\nTrường Nhất Tiếu nhìn chằm chằm theo bóng lưng của Hỗ Gia Danh rồi đột nhiên hạ ánh mắt xuống.\n\n\nHắn có thể thấy một số quân cờ mà Hỗ Gia Danh vẫn chưa đưa ra.\n\n\nKhông phải là Trường Nhất Tiếu chỉ ngồi không mà không nghĩ ra kế sách gì. Dĩ nhiên là hắn đã có kế hoạch. Cũng vì thế nên hắn mới phải luôn tự hỏi.\n\n\nKế hoạch của hắn có thực sự tốt hơn kế hoạch của Hỗ Gia Danh vừa nghĩ ra không?\n\n\nTại sao hắn phải làm khó mọi chuyện hơn trong khi hắn rõ ràng là có cách để khiến kẻ địch rơi vào hỗn loạn?\n\n\nLà do mỹ học mà Hỗ Gia Danh đã nói sao? Hay một nguyên tắc kỳ lạ nào đó đang kìm hãm hắn mà hắn không hề hay biết?\n\n\nHay là......\n\n\nHay là hắn đang sợ? Sợ rằng phải tận mắt chứng kiến sự kết thúc của mọi thứ......\n\n\nLoạt soạt.\n\n\nTrường Nhất Tiếu vò đầu. Mái tóc dài rũ xuống gương mặt trắng bệch.\n\n\n“Trò tiêu khiển......”\n\n\nHắn ta cười nhạt, một nụ cười khó có thể thấy ở hắn thường ngày.\n\n\nHắn nhận ra bản thân đã khác đi rất nhiều. Dù biết nhưng hắn vẫn không thể làm gì cả. Chỉ có thể chấp nhận.\n\n\nNhưng Hỗ Gia Danh lại không như thế. Hỗ Gia Danh muốn hắn phải chơi đùa và tận hưởng với mọi thứ hệt như khi xưa.\n\n\n“Nếu vậy thì ta......”\n\n\nÁnh mắt của Trường Nhất Tiếu trở nên tăm tối.\n\n\nVẻ gian manh trong đôi mắt thường ngày của hắn biến mất. Trong đôi mắt hoang vắng của hắn bắt đầu xuất hiện một thứ gì đó kỳ lạ.",
  "status": "ok"
}